{"status":"REQUEST_SUCCEEDED","responseTime":124,"message":[],"Results":{
"series":
[{"seriesID":"SMU16000006500000011","data":[{"year":"2025","period":"M04","periodName":"April","latest":"true","value":"1192.95","footnotes":[{"code":"P","text":"Preliminary"}]},{"year":"2025","period":"M03","periodName":"March","value":"1162.66","footnotes":[{}]},{"year":"2025","period":"M02","periodName":"February","value":"1174.01","footnotes":[{}]},{"year":"2025","period":"M01","periodName":"January","value":"1146.69","footnotes":[{}]},{"year":"2024","period":"M12","periodName":"December","value":"1159.82","footnotes":[{}]},{"year":"2024","period":"M11","periodName":"November","value":"1142.10","footnotes":[{}]},{"year":"2024","period":"M10","periodName":"October","value":"1154.46","footnotes":[{}]},{"year":"2024","period":"M09","periodName":"September","value":"1125.21","footnotes":[{}]},{"year":"2024","period":"M08","periodName":"August","value":"1087.86","footnotes":[{}]},{"year":"2024","period":"M07","periodName":"July","value":"1094.28","footnotes":[{}]},{"year":"2024","period":"M06","periodName":"June","value":"1105.17","footnotes":[{}]},{"year":"2024","period":"M05","periodName":"May","value":"1087.86","footnotes":[{}]},{"year":"2024","period":"M04","periodName":"April","value":"1083.32","footnotes":[{}]},{"year":"2024","period":"M03","periodName":"March","value":"1029.41","footnotes":[{}]},{"year":"2024","period":"M02","periodName":"February","value":"1036.83","footnotes":[{}]},{"year":"2024","period":"M01","periodName":"January","value":"1011.94","footnotes":[{}]},{"year":"2023","period":"M12","periodName":"December","value":"1011.36","footnotes":[{}]},{"year":"2023","period":"M11","periodName":"November","value":"1000.37","footnotes":[{}]},{"year":"2023","period":"M10","periodName":"October","value":"980.94","footnotes":[{}]},{"year":"2023","period":"M09","periodName":"September","value":"953.88","footnotes":[{}]},{"year":"2023","period":"M08","periodName":"August","value":"934.83","footnotes":[{}]},{"year":"2023","period":"M07","periodName":"July","value":"922.15","footnotes":[{}]},{"year":"2023","period":"M06","periodName":"June","value":"877.79","footnotes":[{}]},{"year":"2023","period":"M05","periodName":"May","value":"860.40","footnotes":[{}]},{"year":"2023","period":"M04","periodName":"April","value":"881.09","footnotes":[{}]},{"year":"2023","period":"M03","periodName":"March","value":"857.85","footnotes":[{}]},{"year":"2023","period":"M02","periodName":"February","value":"858.30","footnotes":[{}]},{"year":"2023","period":"M01","periodName":"January","value":"883.89","footnotes":[{}]},{"year":"2022","period":"M12","periodName":"December","value":"824.14","footnotes":[{}]},{"year":"2022","period":"M11","periodName":"November","value":"824.60","footnotes":[{}]},{"year":"2022","period":"M10","periodName":"October","value":"853.05","footnotes":[{}]},{"year":"2022","period":"M09","periodName":"September","value":"800.66","footnotes":[{}]},{"year":"2022","period":"M08","periodName":"August","value":"778.93","footnotes":[{}]},{"year":"2022","period":"M07","periodName":"July","value":"740.20","footnotes":[{}]},{"year":"2022","period":"M06","periodName":"June","value":"756.71","footnotes":[{}]},{"year":"2022","period":"M05","periodName":"May","value":"767.23","footnotes":[{}]},{"year":"2022","period":"M04","periodName":"April","value":"743.70","footnotes":[{}]},{"year":"2022","period":"M03","periodName":"March","value":"750.61","footnotes":[{}]},{"year":"2022","period":"M02","periodName":"February","value":"757.35","footnotes":[{}]},{"year":"2022","period":"M01","periodName":"January","value":"767.81","footnotes":[{}]},{"year":"2021","period":"M12","periodName":"December","value":"794.36","footnotes":[{}]},{"year":"2021","period":"M11","periodName":"November","value":"789.63","footnotes":[{}]},{"year":"2021","period":"M10","periodName":"October","value":"783.36","footnotes":[{}]},{"year":"2021","period":"M09","periodName":"September","value":"795.33","footnotes":[{}]},{"year":"2021","period":"M08","periodName":"August","value":"805.72","footnotes":[{}]},{"year":"2021","period":"M07","periodName":"July","value":"783.38","footnotes":[{}]},{"year":"2021","period":"M06","periodName":"June","value":"747.17","footnotes":[{}]},{"year":"2021","period":"M05","periodName":"May","value":"768.63","footnotes":[{}]},{"year":"2021","period":"M04","periodName":"April","value":"750.02","footnotes":[{}]},{"year":"2021","period":"M03","periodName":"March","value":"743.24","footnotes":[{}]},{"year":"2021","period":"M02","periodName":"February","value":"764.29","footnotes":[{}]},{"year":"2021","period":"M01","periodName":"January","value":"763.02","footnotes":[{}]},{"year":"2020","period":"M12","periodName":"December","value":"745.39","footnotes":[{}]},{"year":"2020","period":"M11","periodName":"November","value":"768.83","footnotes":[{}]},{"year":"2020","period":"M10","periodName":"October","value":"730.60","footnotes":[{}]},{"year":"2020","period":"M09","periodName":"September","value":"718.02","footnotes":[{}]},{"year":"2020","period":"M08","periodName":"August","value":"728.35","footnotes":[{}]},{"year":"2020","period":"M07","periodName":"July","value":"698.02","footnotes":[{}]},{"year":"2020","period":"M06","periodName":"June","value":"705.92","footnotes":[{}]},{"year":"2020","period":"M05","periodName":"May","value":"693.78","footnotes":[{}]},{"year":"2020","period":"M04","periodName":"April","value":"661.86","footnotes":[{}]},{"year":"2020","period":"M03","periodName":"March","value":"707.49","footnotes":[{}]},{"year":"2020","period":"M02","periodName":"February","value":"704.93","footnotes":[{}]},{"year":"2020","period":"M01","periodName":"January","value":"666.17","footnotes":[{}]},{"year":"2019","period":"M12","periodName":"December","value":"677.35","footnotes":[{}]},{"year":"2019","period":"M11","periodName":"November","value":"679.14","footnotes":[{}]},{"year":"2019","period":"M10","periodName":"October","value":"672.05","footnotes":[{}]},{"year":"2019","period":"M09","periodName":"September","value":"672.36","footnotes":[{}]},{"year":"2019","period":"M08","periodName":"August","value":"664.30","footnotes":[{}]},{"year":"2019","period":"M07","periodName":"July","value":"666.51","footnotes":[{}]},{"year":"2019","period":"M06","periodName":"June","value":"679.88","footnotes":[{}]},{"year":"2019","period":"M05","periodName":"May","value":"668.51","footnotes":[{}]},{"year":"2019","period":"M04","periodName":"April","value":"670.76","footnotes":[{}]},{"year":"2019","period":"M03","periodName":"March","value":"665.58","footnotes":[{}]},{"year":"2019","period":"M02","periodName":"February","value":"649.90","footnotes":[{}]},{"year":"2019","period":"M01","periodName":"January","value":"648.00","footnotes":[{}]},{"year":"2018","period":"M12","periodName":"December","value":"695.47","footnotes":[{}]},{"year":"2018","period":"M11","periodName":"November","value":"683.89","footnotes":[{}]},{"year":"2018","period":"M10","periodName":"October","value":"678.16","footnotes":[{}]},{"year":"2018","period":"M09","periodName":"September","value":"692.85","footnotes":[{}]},{"year":"2018","period":"M08","periodName":"August","value":"702.11","footnotes":[{}]},{"year":"2018","period":"M07","periodName":"July","value":"718.89","footnotes":[{}]},{"year":"2018","period":"M06","periodName":"June","value":"702.24","footnotes":[{}]},{"year":"2018","period":"M05","periodName":"May","value":"694.62","footnotes":[{}]},{"year":"2018","period":"M04","periodName":"April","value":"708.86","footnotes":[{}]},{"year":"2018","period":"M03","periodName":"March","value":"694.78","footnotes":[{}]},{"year":"2018","period":"M02","periodName":"February","value":"696.71","footnotes":[{}]},{"year":"2018","period":"M01","periodName":"January","value":"701.19","footnotes":[{}]},{"year":"2017","period":"M12","periodName":"December","value":"698.90","footnotes":[{}]},{"year":"2017","period":"M11","periodName":"November","value":"702.05","footnotes":[{}]},{"year":"2017","period":"M10","periodName":"October","value":"689.07","footnotes":[{}]},{"year":"2017","period":"M09","periodName":"September","value":"682.62","footnotes":[{}]},{"year":"2017","period":"M08","periodName":"August","value":"671.95","footnotes":[{}]},{"year":"2017","period":"M07","periodName":"July","value":"706.71","footnotes":[{}]},{"year":"2017","period":"M06","periodName":"June","value":"680.26","footnotes":[{}]},{"year":"2017","period":"M05","periodName":"May","value":"672.90","footnotes":[{}]},{"year":"2017","period":"M04","periodName":"April","value":"692.96","footnotes":[{}]},{"year":"2017","period":"M03","periodName":"March","value":"667.06","footnotes":[{}]},{"year":"2017","period":"M02","periodName":"February","value":"699.90","footnotes":[{}]},{"year":"2017","period":"M01","periodName":"January","value":"689.70","footnotes":[{}]},{"year":"2016","period":"M12","periodName":"December","value":"677.08","footnotes":[{}]},{"year":"2016","period":"M11","periodName":"November","value":"664.05","footnotes":[{}]},{"year":"2016","period":"M10","periodName":"October","value":"675.99","footnotes":[{}]},{"year":"2016","period":"M09","periodName":"September","value":"664.44","footnotes":[{}]},{"year":"2016","period":"M08","periodName":"August","value":"651.20","footnotes":[{}]},{"year":"2016","period":"M07","periodName":"July","value":"663.93","footnotes":[{}]},{"year":"2016","period":"M06","periodName":"June","value":"652.97","footnotes":[{}]},{"year":"2016","period":"M05","periodName":"May","value":"660.21","footnotes":[{}]},{"year":"2016","period":"M04","periodName":"April","value":"647.94","footnotes":[{}]},{"year":"2016","period":"M03","periodName":"March","value":"633.02","footnotes":[{}]},{"year":"2016","period":"M02","periodName":"February","value":"620.62","footnotes":[{}]},{"year":"2016","period":"M01","periodName":"January","value":"621.35","footnotes":[{}]},{"year":"2015","period":"M12","periodName":"December","value":"628.09","footnotes":[{}]},{"year":"2015","period":"M11","periodName":"November","value":"640.84","footnotes":[{}]},{"year":"2015","period":"M10","periodName":"October","value":"621.81","footnotes":[{}]},{"year":"2015","period":"M09","periodName":"September","value":"629.94","footnotes":[{}]},{"year":"2015","period":"M08","periodName":"August","value":"646.88","footnotes":[{}]},{"year":"2015","period":"M07","periodName":"July","value":"630.59","footnotes":[{}]},{"year":"2015","period":"M06","periodName":"June","value":"635.93","footnotes":[{}]},{"year":"2015","period":"M05","periodName":"May","value":"629.83","footnotes":[{}]},{"year":"2015","period":"M04","periodName":"April","value":"647.55","footnotes":[{}]},{"year":"2015","period":"M03","periodName":"March","value":"653.47","footnotes":[{}]},{"year":"2015","period":"M02","periodName":"February","value":"666.30","footnotes":[{}]},{"year":"2015","period":"M01","periodName":"January","value":"656.91","footnotes":[{}]}]}]
}}
