{"status":"REQUEST_SUCCEEDED","responseTime":136,"message":[],"Results":{
"series":
[{"seriesID":"SMU12000007000000011","data":[{"year":"2025","period":"M04","periodName":"April","latest":"true","value":"594.54","footnotes":[{"code":"P","text":"Preliminary"}]},{"year":"2025","period":"M03","periodName":"March","value":"618.52","footnotes":[{}]},{"year":"2025","period":"M02","periodName":"February","value":"607.58","footnotes":[{}]},{"year":"2025","period":"M01","periodName":"January","value":"574.20","footnotes":[{}]},{"year":"2024","period":"M12","periodName":"December","value":"584.67","footnotes":[{}]},{"year":"2024","period":"M11","periodName":"November","value":"561.08","footnotes":[{}]},{"year":"2024","period":"M10","periodName":"October","value":"533.00","footnotes":[{}]},{"year":"2024","period":"M09","periodName":"September","value":"556.25","footnotes":[{}]},{"year":"2024","period":"M08","periodName":"August","value":"562.84","footnotes":[{}]},{"year":"2024","period":"M07","periodName":"July","value":"560.45","footnotes":[{}]},{"year":"2024","period":"M06","periodName":"June","value":"573.25","footnotes":[{}]},{"year":"2024","period":"M05","periodName":"May","value":"588.87","footnotes":[{}]},{"year":"2024","period":"M04","periodName":"April","value":"599.49","footnotes":[{}]},{"year":"2024","period":"M03","periodName":"March","value":"614.65","footnotes":[{}]},{"year":"2024","period":"M02","periodName":"February","value":"602.70","footnotes":[{}]},{"year":"2024","period":"M01","periodName":"January","value":"587.59","footnotes":[{}]},{"year":"2023","period":"M12","periodName":"December","value":"600.48","footnotes":[{}]},{"year":"2023","period":"M11","periodName":"November","value":"599.49","footnotes":[{}]},{"year":"2023","period":"M10","periodName":"October","value":"584.82","footnotes":[{}]},{"year":"2023","period":"M09","periodName":"September","value":"564.68","footnotes":[{}]},{"year":"2023","period":"M08","periodName":"August","value":"562.30","footnotes":[{}]},{"year":"2023","period":"M07","periodName":"July","value":"581.35","footnotes":[{}]},{"year":"2023","period":"M06","periodName":"June","value":"577.12","footnotes":[{}]},{"year":"2023","period":"M05","periodName":"May","value":"582.73","footnotes":[{}]},{"year":"2023","period":"M04","periodName":"April","value":"581.98","footnotes":[{}]},{"year":"2023","period":"M03","periodName":"March","value":"584.75","footnotes":[{}]},{"year":"2023","period":"M02","periodName":"February","value":"588.16","footnotes":[{}]},{"year":"2023","period":"M01","periodName":"January","value":"569.92","footnotes":[{}]},{"year":"2022","period":"M12","periodName":"December","value":"567.20","footnotes":[{}]},{"year":"2022","period":"M11","periodName":"November","value":"552.62","footnotes":[{}]},{"year":"2022","period":"M10","periodName":"October","value":"549.98","footnotes":[{}]},{"year":"2022","period":"M09","periodName":"September","value":"534.27","footnotes":[{}]},{"year":"2022","period":"M08","periodName":"August","value":"533.66","footnotes":[{}]},{"year":"2022","period":"M07","periodName":"July","value":"541.48","footnotes":[{}]},{"year":"2022","period":"M06","periodName":"June","value":"541.20","footnotes":[{}]},{"year":"2022","period":"M05","periodName":"May","value":"554.05","footnotes":[{}]},{"year":"2022","period":"M04","periodName":"April","value":"560.62","footnotes":[{}]},{"year":"2022","period":"M03","periodName":"March","value":"575.07","footnotes":[{}]},{"year":"2022","period":"M02","periodName":"February","value":"552.05","footnotes":[{}]},{"year":"2022","period":"M01","periodName":"January","value":"540.93","footnotes":[{}]},{"year":"2021","period":"M12","periodName":"December","value":"532.05","footnotes":[{}]},{"year":"2021","period":"M11","periodName":"November","value":"520.24","footnotes":[{}]},{"year":"2021","period":"M10","periodName":"October","value":"522.36","footnotes":[{}]},{"year":"2021","period":"M09","periodName":"September","value":"493.20","footnotes":[{}]},{"year":"2021","period":"M08","periodName":"August","value":"498.88","footnotes":[{}]},{"year":"2021","period":"M07","periodName":"July","value":"500.46","footnotes":[{}]},{"year":"2021","period":"M06","periodName":"June","value":"508.73","footnotes":[{}]},{"year":"2021","period":"M05","periodName":"May","value":"508.03","footnotes":[{}]},{"year":"2021","period":"M04","periodName":"April","value":"502.56","footnotes":[{}]},{"year":"2021","period":"M03","periodName":"March","value":"482.80","footnotes":[{}]},{"year":"2021","period":"M02","periodName":"February","value":"462.31","footnotes":[{}]},{"year":"2021","period":"M01","periodName":"January","value":"448.20","footnotes":[{}]},{"year":"2020","period":"M12","periodName":"December","value":"447.83","footnotes":[{}]},{"year":"2020","period":"M11","periodName":"November","value":"444.08","footnotes":[{}]},{"year":"2020","period":"M10","periodName":"October","value":"446.34","footnotes":[{}]},{"year":"2020","period":"M09","periodName":"September","value":"441.18","footnotes":[{}]},{"year":"2020","period":"M08","periodName":"August","value":"428.53","footnotes":[{}]},{"year":"2020","period":"M07","periodName":"July","value":"425.53","footnotes":[{}]},{"year":"2020","period":"M06","periodName":"June","value":"438.90","footnotes":[{}]},{"year":"2020","period":"M05","periodName":"May","value":"439.52","footnotes":[{}]},{"year":"2020","period":"M04","periodName":"April","value":"410.96","footnotes":[{}]},{"year":"2020","period":"M03","periodName":"March","value":"451.98","footnotes":[{}]},{"year":"2020","period":"M02","periodName":"February","value":"468.99","footnotes":[{}]},{"year":"2020","period":"M01","periodName":"January","value":"457.85","footnotes":[{}]},{"year":"2019","period":"M12","periodName":"December","value":"457.23","footnotes":[{}]},{"year":"2019","period":"M11","periodName":"November","value":"451.71","footnotes":[{}]},{"year":"2019","period":"M10","periodName":"October","value":"440.76","footnotes":[{}]},{"year":"2019","period":"M09","periodName":"September","value":"428.89","footnotes":[{}]},{"year":"2019","period":"M08","periodName":"August","value":"434.38","footnotes":[{}]},{"year":"2019","period":"M07","periodName":"July","value":"442.00","footnotes":[{}]},{"year":"2019","period":"M06","periodName":"June","value":"455.68","footnotes":[{}]},{"year":"2019","period":"M05","periodName":"May","value":"459.25","footnotes":[{}]},{"year":"2019","period":"M04","periodName":"April","value":"471.52","footnotes":[{}]},{"year":"2019","period":"M03","periodName":"March","value":"486.18","footnotes":[{}]},{"year":"2019","period":"M02","periodName":"February","value":"481.38","footnotes":[{}]},{"year":"2019","period":"M01","periodName":"January","value":"462.20","footnotes":[{}]},{"year":"2018","period":"M12","periodName":"December","value":"464.97","footnotes":[{}]},{"year":"2018","period":"M11","periodName":"November","value":"457.69","footnotes":[{}]},{"year":"2018","period":"M10","periodName":"October","value":"442.48","footnotes":[{}]},{"year":"2018","period":"M09","periodName":"September","value":"435.16","footnotes":[{}]},{"year":"2018","period":"M08","periodName":"August","value":"442.96","footnotes":[{}]},{"year":"2018","period":"M07","periodName":"July","value":"452.87","footnotes":[{}]},{"year":"2018","period":"M06","periodName":"June","value":"447.71","footnotes":[{}]},{"year":"2018","period":"M05","periodName":"May","value":"450.07","footnotes":[{}]},{"year":"2018","period":"M04","periodName":"April","value":"469.80","footnotes":[{}]},{"year":"2018","period":"M03","periodName":"March","value":"478.93","footnotes":[{}]},{"year":"2018","period":"M02","periodName":"February","value":"474.52","footnotes":[{}]},{"year":"2018","period":"M01","periodName":"January","value":"450.99","footnotes":[{}]},{"year":"2017","period":"M12","periodName":"December","value":"441.48","footnotes":[{}]},{"year":"2017","period":"M11","periodName":"November","value":"436.67","footnotes":[{}]},{"year":"2017","period":"M10","periodName":"October","value":"434.15","footnotes":[{}]},{"year":"2017","period":"M09","periodName":"September","value":"383.00","footnotes":[{}]},{"year":"2017","period":"M08","periodName":"August","value":"422.69","footnotes":[{}]},{"year":"2017","period":"M07","periodName":"July","value":"425.72","footnotes":[{}]},{"year":"2017","period":"M06","periodName":"June","value":"421.40","footnotes":[{}]},{"year":"2017","period":"M05","periodName":"May","value":"429.94","footnotes":[{}]},{"year":"2017","period":"M04","periodName":"April","value":"450.26","footnotes":[{}]},{"year":"2017","period":"M03","periodName":"March","value":"455.88","footnotes":[{}]},{"year":"2017","period":"M02","periodName":"February","value":"443.59","footnotes":[{}]},{"year":"2017","period":"M01","periodName":"January","value":"433.85","footnotes":[{}]},{"year":"2016","period":"M12","periodName":"December","value":"425.98","footnotes":[{}]},{"year":"2016","period":"M11","periodName":"November","value":"426.73","footnotes":[{}]},{"year":"2016","period":"M10","periodName":"October","value":"412.92","footnotes":[{}]},{"year":"2016","period":"M09","periodName":"September","value":"405.38","footnotes":[{}]},{"year":"2016","period":"M08","periodName":"August","value":"407.71","footnotes":[{}]},{"year":"2016","period":"M07","periodName":"July","value":"413.48","footnotes":[{}]},{"year":"2016","period":"M06","periodName":"June","value":"408.85","footnotes":[{}]},{"year":"2016","period":"M05","periodName":"May","value":"412.62","footnotes":[{}]},{"year":"2016","period":"M04","periodName":"April","value":"418.60","footnotes":[{}]},{"year":"2016","period":"M03","periodName":"March","value":"421.39","footnotes":[{}]},{"year":"2016","period":"M02","periodName":"February","value":"419.41","footnotes":[{}]},{"year":"2016","period":"M01","periodName":"January","value":"407.38","footnotes":[{}]},{"year":"2015","period":"M12","periodName":"December","value":"403.70","footnotes":[{}]},{"year":"2015","period":"M11","periodName":"November","value":"404.97","footnotes":[{}]},{"year":"2015","period":"M10","periodName":"October","value":"394.85","footnotes":[{}]},{"year":"2015","period":"M09","periodName":"September","value":"384.75","footnotes":[{}]},{"year":"2015","period":"M08","periodName":"August","value":"396.76","footnotes":[{}]},{"year":"2015","period":"M07","periodName":"July","value":"395.87","footnotes":[{}]},{"year":"2015","period":"M06","periodName":"June","value":"390.29","footnotes":[{}]},{"year":"2015","period":"M05","periodName":"May","value":"400.04","footnotes":[{}]},{"year":"2015","period":"M04","periodName":"April","value":"407.26","footnotes":[{}]},{"year":"2015","period":"M03","periodName":"March","value":"418.44","footnotes":[{}]},{"year":"2015","period":"M02","periodName":"February","value":"423.99","footnotes":[{}]},{"year":"2015","period":"M01","periodName":"January","value":"412.08","footnotes":[{}]}]}]
}}
